sqlcipher3/__init__.py
sqlcipher3/_sqlite3.cp312-win32.pyd
sqlcipher3/dbapi2.py
sqlcipher3-0.6.2.dist-info/licenses/LICENSE
sqlcipher3-0.6.2.dist-info/METADATA
sqlcipher3-0.6.2.dist-info/WHEEL
sqlcipher3-0.6.2.dist-info/top_level.txt
sqlcipher3-0.6.2.dist-info/RECORD
