Metadata-Version: 2.4
Name: sqlcipher3
Version: 0.6.2
Summary: DB-API 2.0 interface for SQLCipher 4.x
Author-email: Charles Leifer <coleifer@gmail.com>, laggykiller <chaudominic2@gmail.com>
License-Expression: MIT
Project-URL: Repository, https://github.com/coleifer/sqlcipher3
Classifier: Programming Language :: Python
Classifier: Programming Language :: Python :: 3
Classifier: Programming Language :: C
Classifier: Topic :: Database
Classifier: Topic :: Database :: Database Engines/Servers
Classifier: Topic :: Database :: Front-Ends
Classifier: Topic :: Software Development
Classifier: Topic :: Software Development :: Libraries :: Python Modules
Requires-Python: >=3.9
License-File: LICENSE
Dynamic: license-file
